{
  "version": 1,
  "createdAt": "2026-04-18T03:17:00.228Z",
  "width": 1813.3333740234375,
  "height": 1037.77783203125,
  "strokes": [
    {
      "color": "#000000",
      "outlineColor": "#000000",
      "outlineWidth": 0,
      "options": {
        "size": 12,
        "thinning": 0.5,
        "smoothing": 0.5,
        "streamline": 0.5,
        "easing": "linear",
        "taperStart": 0,
        "taperEnd": 0,
        "capStart": true,
        "capEnd": true
      },
      "startedAt": 1776482193112,
      "points": [
        {
          "x": 473.498291015625,
          "y": 454.98699951171875,
          "p": 0.5,
          "t": 0,
          "tiltX": 0,
          "tiltY": 0
        },
        {
          "x": 471.5625305175781,
          "y": 452.40887451171875,
          "p": 0.5,
          "t": 7.100000023841858,
          "tiltX": 0,
          "tiltY": 0
        },
        {
          "x": 467.6692810058594,
          "y": 447.7387390136719,
          "p": 0.5,
          "t": 7.100000023841858,
          "tiltX": 0,
          "tiltY": 0
        },
        {
          "x": 464.0538330078125,
          "y": 444.8481140136719,
          "p": 0.5,
          "t": 18,
          "tiltX": 0,
          "tiltY": 0
        },
        {
          "x": 463.0555725097656,
          "y": 444.1797180175781,
          "p": 0.5,
          "t": 33.60000002384186,
          "tiltX": 0,
          "tiltY": 0
        },
        {
          "x": 457.6085205078125,
          "y": 441.8446350097656,
          "p": 0.5,
          "t": 33.60000002384186,
          "tiltX": 0,
          "tiltY": 0
        },
        {
          "x": 449.9349060058594,
          "y": 440.138916015625,
          "p": 0.5,
          "t": 51.299999952316284,
          "tiltX": 0,
          "tiltY": 0
        },
        {
          "x": 438.92364501953125,
          "y": 440.138916015625,
          "p": 0.5,
          "t": 51.299999952316284,
          "tiltX": 0,
          "tiltY": 0
        },
        {
          "x": 426.8012390136719,
          "y": 441.0677185058594,
          "p": 0.5,
          "t": 51.299999952316284,
          "tiltX": 0,
          "tiltY": 0
        },
        {
          "x": 413.5633850097656,
          "y": 443.90191650390625,
          "p": 0.5,
          "t": 67.89999997615814,
          "tiltX": 0,
          "tiltY": 0
        },
        {
          "x": 402.3741455078125,
          "y": 449.4922180175781,
          "p": 0.5,
          "t": 67.89999997615814,
          "tiltX": 0,
          "tiltY": 0
        },
        {
          "x": 397.7040100097656,
          "y": 453.381103515625,
          "p": 0.5,
          "t": 84.60000002384186,
          "tiltX": 0,
          "tiltY": 0
        },
        {
          "x": 389.1927185058594,
          "y": 463.77606201171875,
          "p": 0.5,
          "t": 84.60000002384186,
          "tiltX": 0,
          "tiltY": 0
        },
        {
          "x": 384.52691650390625,
          "y": 475.8941345214844,
          "p": 0.5,
          "t": 100.70000004768372,
          "tiltX": 0,
          "tiltY": 0
        },
        {
          "x": 380.65972900390625,
          "y": 491.349853515625,
          "p": 0.5,
          "t": 100.70000004768372,
          "tiltX": 0,
          "tiltY": 0
        },
        {
          "x": 380.65972900390625,
          "y": 509.0321350097656,
          "p": 0.5,
          "t": 117.89999997615814,
          "tiltX": 0,
          "tiltY": 0
        },
        {
          "x": 381.5364685058594,
          "y": 517.8125,
          "p": 0.5,
          "t": 117.89999997615814,
          "tiltX": 0,
          "tiltY": 0
        },
        {
          "x": 386.19793701171875,
          "y": 529.9306030273438,
          "p": 0.5,
          "t": 134.60000002384186,
          "tiltX": 0,
          "tiltY": 0
        },
        {
          "x": 387.248291015625,
          "y": 532.03564453125,
          "p": 0.5,
          "t": 134.60000002384186,
          "tiltX": 0,
          "tiltY": 0
        },
        {
          "x": 393.2118225097656,
          "y": 537.9991455078125,
          "p": 0.5,
          "t": 134.60000002384186,
          "tiltX": 0,
          "tiltY": 0
        },
        {
          "x": 403.6067810058594,
          "y": 546.506103515625,
          "p": 0.5,
          "t": 151.20000004768372,
          "tiltX": 0,
          "tiltY": 0
        },
        {
          "x": 412.3871765136719,
          "y": 550.0173950195312,
          "p": 0.5,
          "t": 151.20000004768372,
          "tiltX": 0,
          "tiltY": 0
        },
        {
          "x": 422.28302001953125,
          "y": 552.7127075195312,
          "p": 0.5,
          "t": 167.89999997615814,
          "tiltX": 0,
          "tiltY": 0
        },
        {
          "x": 434.40106201171875,
          "y": 554.57470703125,
          "p": 0.5,
          "t": 167.89999997615814,
          "tiltX": 0,
          "tiltY": 0
        },
        {
          "x": 448.74566650390625,
          "y": 554.57470703125,
          "p": 0.5,
          "t": 184.20000004768372,
          "tiltX": 0,
          "tiltY": 0
        },
        {
          "x": 464.201416015625,
          "y": 551.6753540039062,
          "p": 0.5,
          "t": 184.20000004768372,
          "tiltX": 0,
          "tiltY": 0
        },
        {
          "x": 477.7257080078125,
          "y": 543.9453125,
          "p": 0.5,
          "t": 201.20000004768372,
          "tiltX": 0,
          "tiltY": 0
        },
        {
          "x": 490.2821350097656,
          "y": 534.279541015625,
          "p": 0.5,
          "t": 201.20000004768372,
          "tiltX": 0,
          "tiltY": 0
        },
        {
          "x": 504.2144470214844,
          "y": 519.3446655273438,
          "p": 0.5,
          "t": 201.20000004768372,
          "tiltX": 0,
          "tiltY": 0
        },
        {
          "x": 516.2847290039062,
          "y": 500.2257080078125,
          "p": 0.5,
          "t": 217.70000004768372,
          "tiltX": 0,
          "tiltY": 0
        },
        {
          "x": 524.2925415039062,
          "y": 480.2040100097656,
          "p": 0.5,
          "t": 217.70000004768372,
          "tiltX": 0,
          "tiltY": 0
        },
        {
          "x": 535.66845703125,
          "y": 443.54168701171875,
          "p": 0.5,
          "t": 234.5,
          "tiltX": 0,
          "tiltY": 0
        },
        {
          "x": 542.2786865234375,
          "y": 413.7803955078125,
          "p": 0.5,
          "t": 234.5,
          "tiltX": 0,
          "tiltY": 0
        },
        {
          "x": 543.1553955078125,
          "y": 404.99566650390625,
          "p": 0.5,
          "t": 251.20000004768372,
          "tiltX": 0,
          "tiltY": 0
        },
        {
          "x": 547.3134155273438,
          "y": 377.95574951171875,
          "p": 0.5,
          "t": 251.20000004768372,
          "tiltX": 0,
          "tiltY": 0
        },
        {
          "x": 549.3142700195312,
          "y": 356.9314270019531,
          "p": 0.5,
          "t": 267.5,
          "tiltX": 0,
          "tiltY": 0
        },
        {
          "x": 551.2630615234375,
          "y": 340.3602600097656,
          "p": 0.5,
          "t": 267.5,
          "tiltX": 0,
          "tiltY": 0
        },
        {
          "x": 552.8993530273438,
          "y": 333.7977600097656,
          "p": 0.5,
          "t": 284.60000002384186,
          "tiltX": 0,
          "tiltY": 0
        },
        {
          "x": 553.5416870117188,
          "y": 330.57293701171875,
          "p": 0.5,
          "t": 284.60000002384186,
          "tiltX": 0,
          "tiltY": 0
        },
        {
          "x": 553.5416870117188,
          "y": 330.1172180175781,
          "p": 0.5,
          "t": 284.60000002384186,
          "tiltX": 0,
          "tiltY": 0
        },
        {
          "x": 553.7673950195312,
          "y": 330.1172180175781,
          "p": 0.5,
          "t": 300.39999997615814,
          "tiltX": 0,
          "tiltY": 0
        },
        {
          "x": 553.7673950195312,
          "y": 330.3428955078125,
          "p": 0.5,
          "t": 317.7999999523163,
          "tiltX": 0,
          "tiltY": 0
        },
        {
          "x": 553.7673950195312,
          "y": 330.7942810058594,
          "p": 0.5,
          "t": 334.5,
          "tiltX": 0,
          "tiltY": 0
        },
        {
          "x": 554.4878540039062,
          "y": 335.1258850097656,
          "p": 0.5,
          "t": 334.5,
          "tiltX": 0,
          "tiltY": 0
        },
        {
          "x": 555.3385620117188,
          "y": 342.795166015625,
          "p": 0.5,
          "t": 350.60000002384186,
          "tiltX": 0,
          "tiltY": 0
        },
        {
          "x": 556.154541015625,
          "y": 349.3533020019531,
          "p": 0.5,
          "t": 350.60000002384186,
          "tiltX": 0,
          "tiltY": 0
        },
        {
          "x": 556.154541015625,
          "y": 363.69793701171875,
          "p": 0.5,
          "t": 350.60000002384186,
          "tiltX": 0,
          "tiltY": 0
        },
        {
          "x": 556.154541015625,
          "y": 385.8290100097656,
          "p": 0.5,
          "t": 367,
          "tiltX": 0,
          "tiltY": 0
        },
        {
          "x": 554.9392700195312,
          "y": 421.0286560058594,
          "p": 0.5,
          "t": 367,
          "tiltX": 0,
          "tiltY": 0
        },
        {
          "x": 554.9392700195312,
          "y": 456.22833251953125,
          "p": 0.5,
          "t": 384.5,
          "tiltX": 0,
          "tiltY": 0
        },
        {
          "x": 553.5807495117188,
          "y": 499.592041015625,
          "p": 0.5,
          "t": 384.5,
          "tiltX": 0,
          "tiltY": 0
        },
        {
          "x": 554.84375,
          "y": 537.5130615234375,
          "p": 0.5,
          "t": 401.10000002384186,
          "tiltX": 0,
          "tiltY": 0
        },
        {
          "x": 554.84375,
          "y": 542.9557495117188,
          "p": 0.5,
          "t": 401.10000002384186,
          "tiltX": 0,
          "tiltY": 0
        },
        {
          "x": 556.8446655273438,
          "y": 563.9757080078125,
          "p": 0.5,
          "t": 417.89999997615814,
          "tiltX": 0,
          "tiltY": 0
        },
        {
          "x": 558.48095703125,
          "y": 570.5338745117188,
          "p": 0.5,
          "t": 417.89999997615814,
          "tiltX": 0,
          "tiltY": 0
        },
        {
          "x": 558.48095703125,
          "y": 570.7595825195312,
          "p": 0.5,
          "t": 434.60000002384186,
          "tiltX": 0,
          "tiltY": 0
        },
        {
          "x": 558.48095703125,
          "y": 570.529541015625,
          "p": 0.5,
          "t": 450.7999999523163,
          "tiltX": 0,
          "tiltY": 0
        },
        {
          "x": 558.48095703125,
          "y": 570.0737915039062,
          "p": 0.5,
          "t": 450.7999999523163,
          "tiltX": 0,
          "tiltY": 0
        },
        {
          "x": 558.48095703125,
          "y": 569.6181030273438,
          "p": 0.5,
          "t": 467.89999997615814,
          "tiltX": 0,
          "tiltY": 0
        },
        {
          "x": 558.48095703125,
          "y": 565.2821655273438,
          "p": 0.5,
          "t": 467.89999997615814,
          "tiltX": 0,
          "tiltY": 0
        },
        {
          "x": 556.72314453125,
          "y": 556.4974365234375,
          "p": 0.5,
          "t": 483.60000002384186,
          "tiltX": 0,
          "tiltY": 0
        },
        {
          "x": 554.96533203125,
          "y": 547.7127075195312,
          "p": 0.5,
          "t": 483.60000002384186,
          "tiltX": 0,
          "tiltY": 0
        },
        {
          "x": 551.29345703125,
          "y": 536.701416015625,
          "p": 0.5,
          "t": 501,
          "tiltX": 0,
          "tiltY": 0
        },
        {
          "x": 547.5087280273438,
          "y": 523.4635620117188,
          "p": 0.5,
          "t": 501,
          "tiltX": 0,
          "tiltY": 0
        },
        {
          "x": 544.80908203125,
          "y": 513.5634155273438,
          "p": 0.5,
          "t": 501,
          "tiltX": 0,
          "tiltY": 0
        },
        {
          "x": 540.1432495117188,
          "y": 501.4410095214844,
          "p": 0.5,
          "t": 517.7999999523163,
          "tiltX": 0,
          "tiltY": 0
        },
        {
          "x": 534.5486450195312,
          "y": 490.25177001953125,
          "p": 0.5,
          "t": 517.7999999523163,
          "tiltX": 0,
          "tiltY": 0
        },
        {
          "x": 524.65283203125,
          "y": 473.4331970214844,
          "p": 0.5,
          "t": 534.6000000238419,
          "tiltX": 0,
          "tiltY": 0
        },
        {
          "x": 518.2291870117188,
          "y": 464.2578430175781,
          "p": 0.5,
          "t": 534.6000000238419,
          "tiltX": 0,
          "tiltY": 0
        },
        {
          "x": 505.6684265136719,
          "y": 454.592041015625,
          "p": 0.5,
          "t": 551.2000000476837,
          "tiltX": 0,
          "tiltY": 0
        },
        {
          "x": 497.76043701171875,
          "y": 450.1996765136719,
          "p": 0.5,
          "t": 551.2000000476837,
          "tiltX": 0,
          "tiltY": 0
        },
        {
          "x": 494.5356140136719,
          "y": 449.552978515625,
          "p": 0.5,
          "t": 567.8999999761581,
          "tiltX": 0,
          "tiltY": 0
        },
        {
          "x": 487.9731140136719,
          "y": 449.552978515625,
          "p": 0.5,
          "t": 567.8999999761581,
          "tiltX": 0,
          "tiltY": 0
        },
        {
          "x": 480.29949951171875,
          "y": 452.1094055175781,
          "p": 0.5,
          "t": 584.5,
          "tiltX": 0,
          "tiltY": 0
        },
        {
          "x": 473.26824951171875,
          "y": 457.37847900390625,
          "p": 0.5,
          "t": 584.5,
          "tiltX": 0,
          "tiltY": 0
        },
        {
          "x": 466.8446350097656,
          "y": 466.54949951171875,
          "p": 0.5,
          "t": 584.5,
          "tiltX": 0,
          "tiltY": 0
        },
        {
          "x": 464.28387451171875,
          "y": 474.2187805175781,
          "p": 0.5,
          "t": 601.2999999523163,
          "tiltX": 0,
          "tiltY": 0
        },
        {
          "x": 461.4453430175781,
          "y": 487.4522705078125,
          "p": 0.5,
          "t": 601.2999999523163,
          "tiltX": 0,
          "tiltY": 0
        },
        {
          "x": 461.4453430175781,
          "y": 501.7969055175781,
          "p": 0.5,
          "t": 617.3999999761581,
          "tiltX": 0,
          "tiltY": 0
        },
        {
          "x": 462.22222900390625,
          "y": 507.2395935058594,
          "p": 0.5,
          "t": 634.6000000238419,
          "tiltX": 0,
          "tiltY": 0
        },
        {
          "x": 466.7187805175781,
          "y": 516.232666015625,
          "p": 0.5,
          "t": 634.6000000238419,
          "tiltX": 0,
          "tiltY": 0
        },
        {
          "x": 470.607666015625,
          "y": 520.8984375,
          "p": 0.5,
          "t": 634.6000000238419,
          "tiltX": 0,
          "tiltY": 0
        },
        {
          "x": 475.2734680175781,
          "y": 524.787353515625,
          "p": 0.5,
          "t": 651.2000000476837,
          "tiltX": 0,
          "tiltY": 0
        },
        {
          "x": 479.6050720214844,
          "y": 526.953125,
          "p": 0.5,
          "t": 651.2000000476837,
          "tiltX": 0,
          "tiltY": 0
        },
        {
          "x": 483.9366455078125,
          "y": 527.6736450195312,
          "p": 0.5,
          "t": 651.2000000476837,
          "tiltX": 0,
          "tiltY": 0
        },
        {
          "x": 488.26824951171875,
          "y": 527.6736450195312,
          "p": 0.5,
          "t": 667.2999999523163,
          "tiltX": 0,
          "tiltY": 0
        },
        {
          "x": 492.599853515625,
          "y": 526.2283325195312,
          "p": 0.5,
          "t": 667.2999999523163,
          "tiltX": 0,
          "tiltY": 0
        },
        {
          "x": 496.93145751953125,
          "y": 524.7830200195312,
          "p": 0.5,
          "t": 686.1000000238419,
          "tiltX": 0,
          "tiltY": 0
        },
        {
          "x": 508.1163330078125,
          "y": 518.2552490234375,
          "p": 0.5,
          "t": 686.1000000238419,
          "tiltX": 0,
          "tiltY": 0
        },
        {
          "x": 517.109375,
          "y": 512.85595703125,
          "p": 0.5,
          "t": 701.2000000476837,
          "tiltX": 0,
          "tiltY": 0
        },
        {
          "x": 527.365478515625,
          "y": 506.3281555175781,
          "p": 0.5,
          "t": 701.2000000476837,
          "tiltX": 0,
          "tiltY": 0
        },
        {
          "x": 545.2821655273438,
          "y": 497.365478515625,
          "p": 0.5,
          "t": 717.2000000476837,
          "tiltX": 0,
          "tiltY": 0
        },
        {
          "x": 555.177978515625,
          "y": 494.66583251953125,
          "p": 0.5,
          "t": 717.2000000476837,
          "tiltX": 0,
          "tiltY": 0
        },
        {
          "x": 563.9583740234375,
          "y": 493.7847595214844,
          "p": 0.5,
          "t": 734.5,
          "tiltX": 0,
          "tiltY": 0
        },
        {
          "x": 566.0634155273438,
          "y": 493.7847595214844,
          "p": 0.5,
          "t": 734.5,
          "tiltX": 0,
          "tiltY": 0
        },
        {
          "x": 570.39501953125,
          "y": 493.7847595214844,
          "p": 0.5,
          "t": 734.5,
          "tiltX": 0,
          "tiltY": 0
        },
        {
          "x": 573.615478515625,
          "y": 493.7847595214844,
          "p": 0.5,
          "t": 751.2000000476837,
          "tiltX": 0,
          "tiltY": 0
        },
        {
          "x": 575.7205200195312,
          "y": 494.8350830078125,
          "p": 0.5,
          "t": 751.2000000476837,
          "tiltX": 0,
          "tiltY": 0
        },
        {
          "x": 577.3003540039062,
          "y": 496.4149475097656,
          "p": 0.5,
          "t": 767.6000000238419,
          "tiltX": 0,
          "tiltY": 0
        },
        {
          "x": 578.3507080078125,
          "y": 498.5199890136719,
          "p": 0.5,
          "t": 767.6000000238419,
          "tiltX": 0,
          "tiltY": 0
        },
        {
          "x": 579.6354370117188,
          "y": 501.740478515625,
          "p": 0.5,
          "t": 784.6000000238419,
          "tiltX": 0,
          "tiltY": 0
        },
        {
          "x": 579.96533203125,
          "y": 502.7344055175781,
          "p": 0.5,
          "t": 784.6000000238419,
          "tiltX": 0,
          "tiltY": 0
        },
        {
          "x": 580.685791015625,
          "y": 507.0660095214844,
          "p": 0.5,
          "t": 801.1000000238419,
          "tiltX": 0,
          "tiltY": 0
        },
        {
          "x": 581.328125,
          "y": 510.2864685058594,
          "p": 0.5,
          "t": 801.1000000238419,
          "tiltX": 0,
          "tiltY": 0
        },
        {
          "x": 581.8533325195312,
          "y": 512.3915405273438,
          "p": 0.5,
          "t": 801.1000000238419,
          "tiltX": 0,
          "tiltY": 0
        },
        {
          "x": 581.8533325195312,
          "y": 512.6171875,
          "p": 0.5,
          "t": 818,
          "tiltX": 0,
          "tiltY": 0
        },
        {
          "x": 582.0790405273438,
          "y": 512.8428955078125,
          "p": 0.5,
          "t": 818,
          "tiltX": 0,
          "tiltY": 0
        },
        {
          "x": 582.0790405273438,
          "y": 513.068603515625,
          "p": 0.5,
          "t": 834.6000000238419,
          "tiltX": 0,
          "tiltY": 0
        },
        {
          "x": 582.3046875,
          "y": 513.068603515625,
          "p": 0.5,
          "t": 834.6000000238419,
          "tiltX": 0,
          "tiltY": 0
        },
        {
          "x": 582.756103515625,
          "y": 513.068603515625,
          "p": 0.5,
          "t": 851.2000000476837,
          "tiltX": 0,
          "tiltY": 0
        },
        {
          "x": 585.3298950195312,
          "y": 510.490478515625,
          "p": 0.5,
          "t": 851.2000000476837,
          "tiltX": 0,
          "tiltY": 0
        },
        {
          "x": 588.44189453125,
          "y": 505.8203430175781,
          "p": 0.5,
          "t": 867.8999999761581,
          "tiltX": 0,
          "tiltY": 0
        },
        {
          "x": 592.8298950195312,
          "y": 497.912353515625,
          "p": 0.5,
          "t": 867.8999999761581,
          "tiltX": 0,
          "tiltY": 0
        },
        {
          "x": 595.2864990234375,
          "y": 491.349853515625,
          "p": 0.5,
          "t": 886.1000000238419,
          "tiltX": 0,
          "tiltY": 0
        },
        {
          "x": 598.5634155273438,
          "y": 484.787353515625,
          "p": 0.5,
          "t": 886.1000000238419,
          "tiltX": 0,
          "tiltY": 0
        },
        {
          "x": 603.67626953125,
          "y": 478.8194580078125,
          "p": 0.5,
          "t": 886.1000000238419,
          "tiltX": 0,
          "tiltY": 0
        },
        {
          "x": 603.9019165039062,
          "y": 478.5894470214844,
          "p": 0.5,
          "t": 901.2000000476837,
          "tiltX": 0,
          "tiltY": 0
        },
        {
          "x": 604.3533325195312,
          "y": 478.5894470214844,
          "p": 0.5,
          "t": 901.2000000476837,
          "tiltX": 0,
          "tiltY": 0
        },
        {
          "x": 604.5790405273438,
          "y": 478.5894470214844,
          "p": 0.5,
          "t": 917,
          "tiltX": 0,
          "tiltY": 0
        },
        {
          "x": 605.62939453125,
          "y": 480.6944580078125,
          "p": 0.5,
          "t": 917,
          "tiltX": 0,
          "tiltY": 0
        },
        {
          "x": 607.3307495117188,
          "y": 488.3637390136719,
          "p": 0.5,
          "t": 934.5,
          "tiltX": 0,
          "tiltY": 0
        },
        {
          "x": 608.107666015625,
          "y": 493.80645751953125,
          "p": 0.5,
          "t": 934.5,
          "tiltX": 0,
          "tiltY": 0
        },
        {
          "x": 609.006103515625,
          "y": 503.7022705078125,
          "p": 0.5,
          "t": 951.7999999523163,
          "tiltX": 0,
          "tiltY": 0
        },
        {
          "x": 609.006103515625,
          "y": 504.6961975097656,
          "p": 0.5,
          "t": 951.7999999523163,
          "tiltX": 0,
          "tiltY": 0
        },
        {
          "x": 609.7830200195312,
          "y": 510.138916015625,
          "p": 0.5,
          "t": 967.8999999761581,
          "tiltX": 0,
          "tiltY": 0
        },
        {
          "x": 611.3368530273438,
          "y": 515.5816040039062,
          "p": 0.5,
          "t": 967.8999999761581,
          "tiltX": 0,
          "tiltY": 0
        },
        {
          "x": 612.38720703125,
          "y": 517.6866455078125,
          "p": 0.5,
          "t": 967.8999999761581,
          "tiltX": 0,
          "tiltY": 0
        },
        {
          "x": 612.8385620117188,
          "y": 518.1380615234375,
          "p": 0.5,
          "t": 984.6000000238419,
          "tiltX": 0,
          "tiltY": 0
        },
        {
          "x": 613.0642700195312,
          "y": 518.1380615234375,
          "p": 0.5,
          "t": 984.6000000238419,
          "tiltX": 0,
          "tiltY": 0
        },
        {
          "x": 613.2899780273438,
          "y": 518.1380615234375,
          "p": 0.5,
          "t": 1000.8999999761581,
          "tiltX": 0,
          "tiltY": 0
        },
        {
          "x": 613.515625,
          "y": 517.9080200195312,
          "p": 0.5,
          "t": 1000.8999999761581,
          "tiltX": 0,
          "tiltY": 0
        },
        {
          "x": 613.7413330078125,
          "y": 517.4522705078125,
          "p": 0.5,
          "t": 1017.8999999761581,
          "tiltX": 0,
          "tiltY": 0
        },
        {
          "x": 613.7413330078125,
          "y": 514.2274780273438,
          "p": 0.5,
          "t": 1017.8999999761581,
          "tiltX": 0,
          "tiltY": 0
        },
        {
          "x": 614.4618530273438,
          "y": 509.8915100097656,
          "p": 0.5,
          "t": 1034.5,
          "tiltX": 0,
          "tiltY": 0
        },
        {
          "x": 614.4618530273438,
          "y": 504.4444580078125,
          "p": 0.5,
          "t": 1034.5,
          "tiltX": 0,
          "tiltY": 0
        },
        {
          "x": 615.23876953125,
          "y": 498.9974060058594,
          "p": 0.5,
          "t": 1034.5,
          "tiltX": 0,
          "tiltY": 0
        },
        {
          "x": 616.5234375,
          "y": 495.7725830078125,
          "p": 0.5,
          "t": 1051.2000000476837,
          "tiltX": 0,
          "tiltY": 0
        },
        {
          "x": 616.5234375,
          "y": 495.5425720214844,
          "p": 0.5,
          "t": 1051.2000000476837,
          "tiltX": 0,
          "tiltY": 0
        },
        {
          "x": 616.974853515625,
          "y": 495.5425720214844,
          "p": 0.5,
          "t": 1067.8999999761581,
          "tiltX": 0,
          "tiltY": 0
        },
        {
          "x": 617.42626953125,
          "y": 495.5425720214844,
          "p": 0.5,
          "t": 1067.8999999761581,
          "tiltX": 0,
          "tiltY": 0
        },
        {
          "x": 618.420166015625,
          "y": 495.5425720214844,
          "p": 0.5,
          "t": 1084.6000000238419,
          "tiltX": 0,
          "tiltY": 0
        },
        {
          "x": 619.4140625,
          "y": 496.2066345214844,
          "p": 0.5,
          "t": 1084.6000000238419,
          "tiltX": 0,
          "tiltY": 0
        },
        {
          "x": 620.4080200195312,
          "y": 496.8706970214844,
          "p": 0.5,
          "t": 1101.2000000476837,
          "tiltX": 0,
          "tiltY": 0
        },
        {
          "x": 623.6284790039062,
          "y": 498.8020935058594,
          "p": 0.5,
          "t": 1101.2000000476837,
          "tiltX": 0,
          "tiltY": 0
        },
        {
          "x": 624.0798950195312,
          "y": 499.0278015136719,
          "p": 0.5,
          "t": 1101.2000000476837,
          "tiltX": 0,
          "tiltY": 0
        },
        {
          "x": 624.53125,
          "y": 499.2535095214844,
          "p": 0.5,
          "t": 1117.8999999761581,
          "tiltX": 0,
          "tiltY": 0
        },
        {
          "x": 624.982666015625,
          "y": 499.47918701171875,
          "p": 0.5,
          "t": 1117.8999999761581,
          "tiltX": 0,
          "tiltY": 0
        },
        {
          "x": 625.43408203125,
          "y": 499.47918701171875,
          "p": 0.5,
          "t": 1134.2000000476837,
          "tiltX": 0,
          "tiltY": 0
        },
        {
          "x": 626.427978515625,
          "y": 499.47918701171875,
          "p": 0.5,
          "t": 1134.2000000476837,
          "tiltX": 0,
          "tiltY": 0
        },
        {
          "x": 626.87939453125,
          "y": 499.47918701171875,
          "p": 0.5,
          "t": 1151.2000000476837,
          "tiltX": 0,
          "tiltY": 0
        },
        {
          "x": 627.873291015625,
          "y": 499.47918701171875,
          "p": 0.5,
          "t": 1151.2000000476837,
          "tiltX": 0,
          "tiltY": 0
        },
        {
          "x": 629.453125,
          "y": 497.8949890136719,
          "p": 0.5,
          "t": 1167.8999999761581,
          "tiltX": 0,
          "tiltY": 0
        },
        {
          "x": 629.904541015625,
          "y": 497.43927001953125,
          "p": 0.5,
          "t": 1167.8999999761581,
          "tiltX": 0,
          "tiltY": 0
        },
        {
          "x": 634.5703125,
          "y": 493.5460205078125,
          "p": 0.5,
          "t": 1167.8999999761581,
          "tiltX": 0,
          "tiltY": 0
        },
        {
          "x": 635.5642700195312,
          "y": 492.87762451171875,
          "p": 0.5,
          "t": 1184.6000000238419,
          "tiltX": 0,
          "tiltY": 0
        },
        {
          "x": 636.015625,
          "y": 492.87762451171875,
          "p": 0.5,
          "t": 1184.6000000238419,
          "tiltX": 0,
          "tiltY": 0
        },
        {
          "x": 636.2413330078125,
          "y": 493.10333251953125,
          "p": 0.5,
          "t": 1200.7000000476837,
          "tiltX": 0,
          "tiltY": 0
        },
        {
          "x": 636.467041015625,
          "y": 493.3290100097656,
          "p": 0.5,
          "t": 1218.3999999761581,
          "tiltX": 0,
          "tiltY": 0
        },
        {
          "x": 636.91845703125,
          "y": 493.7803955078125,
          "p": 0.5,
          "t": 1218.3999999761581,
          "tiltX": 0,
          "tiltY": 0
        },
        {
          "x": 637.3698120117188,
          "y": 494.2317810058594,
          "p": 0.5,
          "t": 1234.5,
          "tiltX": 0,
          "tiltY": 0
        },
        {
          "x": 637.8212280273438,
          "y": 494.4574890136719,
          "p": 0.5,
          "t": 1234.5,
          "tiltX": 0,
          "tiltY": 0
        },
        {
          "x": 638.8151245117188,
          "y": 495.1215515136719,
          "p": 0.5,
          "t": 1251.2999999523163,
          "tiltX": 0,
          "tiltY": 0
        },
        {
          "x": 642.03564453125,
          "y": 496.4062805175781,
          "p": 0.5,
          "t": 1251.2999999523163,
          "tiltX": 0,
          "tiltY": 0
        },
        {
          "x": 642.4869995117188,
          "y": 496.4062805175781,
          "p": 0.5,
          "t": 1251.2999999523163,
          "tiltX": 0,
          "tiltY": 0
        },
        {
          "x": 645.70751953125,
          "y": 497.04864501953125,
          "p": 0.5,
          "t": 1267.8999999761581,
          "tiltX": 0,
          "tiltY": 0
        },
        {
          "x": 646.701416015625,
          "y": 497.04864501953125,
          "p": 0.5,
          "t": 1267.8999999761581,
          "tiltX": 0,
          "tiltY": 0
        },
        {
          "x": 651.0330200195312,
          "y": 495.60333251953125,
          "p": 0.5,
          "t": 1284.6000000238419,
          "tiltX": 0,
          "tiltY": 0
        },
        {
          "x": 651.6970825195312,
          "y": 494.6050720214844,
          "p": 0.5,
          "t": 1284.6000000238419,
          "tiltX": 0,
          "tiltY": 0
        },
        {
          "x": 654.2708740234375,
          "y": 492.6692810058594,
          "p": 0.5,
          "t": 1301.2999999523163,
          "tiltX": 0,
          "tiltY": 0
        },
        {
          "x": 656.2022705078125,
          "y": 489.4444580078125,
          "p": 0.5,
          "t": 1301.2999999523163,
          "tiltX": 0,
          "tiltY": 0
        }
      ]
    },
    {
      "color": "#000000",
      "outlineColor": "#000000",
      "outlineWidth": 0,
      "options": {
        "size": 12,
        "thinning": 0.5,
        "smoothing": 0.5,
        "streamline": 0.5,
        "easing": "linear",
        "taperStart": 0,
        "taperEnd": 0,
        "capStart": true,
        "capEnd": true
      },
      "startedAt": 1776482194500,
      "points": [
        {
          "x": 673.9844360351562,
          "y": 458.2725830078125,
          "p": 0.5,
          "t": 0,
          "tiltX": 0,
          "tiltY": 0
        },
        {
          "x": 673.5286865234375,
          "y": 458.498291015625,
          "p": 0.5,
          "t": 13.600000023841858,
          "tiltX": 0,
          "tiltY": 0
        },
        {
          "x": 671.5928955078125,
          "y": 461.7187805175781,
          "p": 0.5,
          "t": 13.600000023841858,
          "tiltX": 0,
          "tiltY": 0
        },
        {
          "x": 670.3038330078125,
          "y": 464.93927001953125,
          "p": 0.5,
          "t": 13.600000023841858,
          "tiltX": 0,
          "tiltY": 0
        },
        {
          "x": 666.7882080078125,
          "y": 473.7196350097656,
          "p": 0.5,
          "t": 29.399999976158142,
          "tiltX": 0,
          "tiltY": 0
        },
        {
          "x": 666.7882080078125,
          "y": 479.162353515625,
          "p": 0.5,
          "t": 29.399999976158142,
          "tiltX": 0,
          "tiltY": 0
        },
        {
          "x": 666.7882080078125,
          "y": 483.49395751953125,
          "p": 0.5,
          "t": 46.10000002384186,
          "tiltX": 0,
          "tiltY": 0
        },
        {
          "x": 666.7882080078125,
          "y": 483.9453430175781,
          "p": 0.5,
          "t": 46.10000002384186,
          "tiltX": 0,
          "tiltY": 0
        },
        {
          "x": 667.3134155273438,
          "y": 486.0503845214844,
          "p": 0.5,
          "t": 62.799999952316284,
          "tiltX": 0,
          "tiltY": 0
        },
        {
          "x": 669.41845703125,
          "y": 487.1007080078125,
          "p": 0.5,
          "t": 62.799999952316284,
          "tiltX": 0,
          "tiltY": 0
        },
        {
          "x": 671.5234985351562,
          "y": 487.6258850097656,
          "p": 0.5,
          "t": 79.39999997615814,
          "tiltX": 0,
          "tiltY": 0
        },
        {
          "x": 674.7439575195312,
          "y": 488.26824951171875,
          "p": 0.5,
          "t": 79.39999997615814,
          "tiltX": 0,
          "tiltY": 0
        },
        {
          "x": 679.0755615234375,
          "y": 488.9887390136719,
          "p": 0.5,
          "t": 96.10000002384186,
          "tiltX": 0,
          "tiltY": 0
        },
        {
          "x": 683.4071655273438,
          "y": 489.709228515625,
          "p": 0.5,
          "t": 96.10000002384186,
          "tiltX": 0,
          "tiltY": 0
        },
        {
          "x": 685.51220703125,
          "y": 489.709228515625,
          "p": 0.5,
          "t": 96.10000002384186,
          "tiltX": 0,
          "tiltY": 0
        },
        {
          "x": 692.0703735351562,
          "y": 490.52520751953125,
          "p": 0.5,
          "t": 112.70000004768372,
          "tiltX": 0,
          "tiltY": 0
        },
        {
          "x": 697.5130615234375,
          "y": 491.3020935058594,
          "p": 0.5,
          "t": 112.70000004768372,
          "tiltX": 0,
          "tiltY": 0
        },
        {
          "x": 705.1823120117188,
          "y": 493.0035095214844,
          "p": 0.5,
          "t": 129.39999997615814,
          "tiltX": 0,
          "tiltY": 0
        },
        {
          "x": 715.0781860351562,
          "y": 496.6015930175781,
          "p": 0.5,
          "t": 129.39999997615814,
          "tiltX": 0,
          "tiltY": 0
        },
        {
          "x": 719.7439575195312,
          "y": 499.71356201171875,
          "p": 0.5,
          "t": 145.5,
          "tiltX": 0,
          "tiltY": 0
        },
        {
          "x": 722.3177490234375,
          "y": 501.6449890136719,
          "p": 0.5,
          "t": 145.5,
          "tiltX": 0,
          "tiltY": 0
        },
        {
          "x": 722.3177490234375,
          "y": 502.09637451171875,
          "p": 0.5,
          "t": 162.60000002384186,
          "tiltX": 0,
          "tiltY": 0
        },
        {
          "x": 722.3177490234375,
          "y": 502.32208251953125,
          "p": 0.5,
          "t": 162.60000002384186,
          "tiltX": 0,
          "tiltY": 0
        },
        {
          "x": 722.0877075195312,
          "y": 502.7734680175781,
          "p": 0.5,
          "t": 162.60000002384186,
          "tiltX": 0,
          "tiltY": 0
        },
        {
          "x": 718.8628540039062,
          "y": 504.70489501953125,
          "p": 0.5,
          "t": 179.39999997615814,
          "tiltX": 0,
          "tiltY": 0
        },
        {
          "x": 714.5269165039062,
          "y": 506.8706970214844,
          "p": 0.5,
          "t": 179.39999997615814,
          "tiltX": 0,
          "tiltY": 0
        },
        {
          "x": 707.9644165039062,
          "y": 510.1475830078125,
          "p": 0.5,
          "t": 195.20000004768372,
          "tiltX": 0,
          "tiltY": 0
        },
        {
          "x": 702.2222290039062,
          "y": 514.2448120117188,
          "p": 0.5,
          "t": 195.20000004768372,
          "tiltX": 0,
          "tiltY": 0
        },
        {
          "x": 697.1050415039062,
          "y": 520.2083740234375,
          "p": 0.5,
          "t": 212.70000004768372,
          "tiltX": 0,
          "tiltY": 0
        },
        {
          "x": 696.0503540039062,
          "y": 522.3134155273438,
          "p": 0.5,
          "t": 212.70000004768372,
          "tiltX": 0,
          "tiltY": 0
        },
        {
          "x": 693.8802490234375,
          "y": 526.64501953125,
          "p": 0.5,
          "t": 229.39999997615814,
          "tiltX": 0,
          "tiltY": 0
        },
        {
          "x": 693.1553955078125,
          "y": 530.9765625,
          "p": 0.5,
          "t": 229.39999997615814,
          "tiltX": 0,
          "tiltY": 0
        },
        {
          "x": 693.1553955078125,
          "y": 533.0816040039062,
          "p": 0.5,
          "t": 229.39999997615814,
          "tiltX": 0,
          "tiltY": 0
        },
        {
          "x": 693.1553955078125,
          "y": 533.5330200195312,
          "p": 0.5,
          "t": 246,
          "tiltX": 0,
          "tiltY": 0
        },
        {
          "x": 693.1553955078125,
          "y": 533.7587280273438,
          "p": 0.5,
          "t": 246,
          "tiltX": 0,
          "tiltY": 0
        },
        {
          "x": 693.381103515625,
          "y": 533.7587280273438,
          "p": 0.5,
          "t": 262.7000000476837,
          "tiltX": 0,
          "tiltY": 0
        },
        {
          "x": 693.6068115234375,
          "y": 533.7587280273438,
          "p": 0.5,
          "t": 279.39999997615814,
          "tiltX": 0,
          "tiltY": 0
        },
        {
          "x": 693.83251953125,
          "y": 533.7587280273438,
          "p": 0.5,
          "t": 279.39999997615814,
          "tiltX": 0,
          "tiltY": 0
        },
        {
          "x": 694.0581665039062,
          "y": 533.5286865234375,
          "p": 0.5,
          "t": 296.10000002384186,
          "tiltX": 0,
          "tiltY": 0
        },
        {
          "x": 694.2838745117188,
          "y": 533.5286865234375,
          "p": 0.5,
          "t": 296.10000002384186,
          "tiltX": 0,
          "tiltY": 0
        },
        {
          "x": 694.2838745117188,
          "y": 533.2986450195312,
          "p": 0.5,
          "t": 312.7000000476837,
          "tiltX": 0,
          "tiltY": 0
        },
        {
          "x": 694.0538330078125,
          "y": 533.2986450195312,
          "p": 0.5,
          "t": 312.7000000476837,
          "tiltX": 0,
          "tiltY": 0
        },
        {
          "x": 693.59814453125,
          "y": 533.5243530273438,
          "p": 0.5,
          "t": 312.7000000476837,
          "tiltX": 0,
          "tiltY": 0
        },
        {
          "x": 692.599853515625,
          "y": 533.5243530273438,
          "p": 0.5,
          "t": 329.10000002384186,
          "tiltX": 0,
          "tiltY": 0
        },
        {
          "x": 689.3750610351562,
          "y": 535.4557495117188,
          "p": 0.5,
          "t": 329.10000002384186,
          "tiltX": 0,
          "tiltY": 0
        },
        {
          "x": 685.0391235351562,
          "y": 537.62158203125,
          "p": 0.5,
          "t": 346.10000002384186,
          "tiltX": 0,
          "tiltY": 0
        },
        {
          "x": 681.4236450195312,
          "y": 540.5078125,
          "p": 0.5,
          "t": 346.10000002384186,
          "tiltX": 0,
          "tiltY": 0
        },
        {
          "x": 679.8394165039062,
          "y": 542.0877075195312,
          "p": 0.5,
          "t": 362.7000000476837,
          "tiltX": 0,
          "tiltY": 0
        },
        {
          "x": 679.8394165039062,
          "y": 543.0816040039062,
          "p": 0.5,
          "t": 362.7000000476837,
          "tiltX": 0,
          "tiltY": 0
        },
        {
          "x": 679.8394165039062,
          "y": 543.3073120117188,
          "p": 0.5,
          "t": 378.7999999523163,
          "tiltX": 0,
          "tiltY": 0
        },
        {
          "x": 680.0651245117188,
          "y": 543.3073120117188,
          "p": 0.5,
          "t": 378.7999999523163,
          "tiltX": 0,
          "tiltY": 0
        },
        {
          "x": 680.2908325195312,
          "y": 543.3073120117188,
          "p": 0.5,
          "t": 396.10000002384186,
          "tiltX": 0,
          "tiltY": 0
        },
        {
          "x": 682.3958740234375,
          "y": 542.2526245117188,
          "p": 0.5,
          "t": 396.10000002384186,
          "tiltX": 0,
          "tiltY": 0
        },
        {
          "x": 686.2847290039062,
          "y": 537.58251953125,
          "p": 0.5,
          "t": 396.10000002384186,
          "tiltX": 0,
          "tiltY": 0
        },
        {
          "x": 690.9505615234375,
          "y": 533.6892700195312,
          "p": 0.5,
          "t": 412.7000000476837,
          "tiltX": 0,
          "tiltY": 0
        },
        {
          "x": 695.0477905273438,
          "y": 527.9470825195312,
          "p": 0.5,
          "t": 412.7000000476837,
          "tiltX": 0,
          "tiltY": 0
        },
        {
          "x": 700.16064453125,
          "y": 521.9791870117188,
          "p": 0.5,
          "t": 428.7000000476837,
          "tiltX": 0,
          "tiltY": 0
        },
        {
          "x": 702.4913330078125,
          "y": 516.5321655273438,
          "p": 0.5,
          "t": 428.7000000476837,
          "tiltX": 0,
          "tiltY": 0
        }
      ]
    },
    {
      "color": "#000000",
      "outlineColor": "#000000",
      "outlineWidth": 0,
      "options": {
        "size": 12,
        "thinning": 0.5,
        "smoothing": 0.5,
        "streamline": 0.5,
        "easing": "linear",
        "taperStart": 0,
        "taperEnd": 0,
        "capStart": true,
        "capEnd": true
      },
      "startedAt": 1776482195031,
      "points": [
        {
          "x": 762.2526245117188,
          "y": 345.6380310058594,
          "p": 0.5,
          "t": 0,
          "tiltX": 0,
          "tiltY": 0
        },
        {
          "x": 762.2526245117188,
          "y": 345.8637390136719,
          "p": 0.5,
          "t": 15.700000047683716,
          "tiltX": 0,
          "tiltY": 0
        },
        {
          "x": 762.4783325195312,
          "y": 346.08941650390625,
          "p": 0.5,
          "t": 15.700000047683716,
          "tiltX": 0,
          "tiltY": 0
        },
        {
          "x": 763.2552490234375,
          "y": 351.5321350097656,
          "p": 0.5,
          "t": 15.700000047683716,
          "tiltX": 0,
          "tiltY": 0
        },
        {
          "x": 764.1710205078125,
          "y": 362.5390930175781,
          "p": 0.5,
          "t": 32.300000071525574,
          "tiltX": 0,
          "tiltY": 0
        },
        {
          "x": 765.1259155273438,
          "y": 376.8836975097656,
          "p": 0.5,
          "t": 32.300000071525574,
          "tiltX": 0,
          "tiltY": 0
        },
        {
          "x": 765.1259155273438,
          "y": 391.22833251953125,
          "p": 0.5,
          "t": 48.89999997615814,
          "tiltX": 0,
          "tiltY": 0
        },
        {
          "x": 765.1259155273438,
          "y": 411.1328430175781,
          "p": 0.5,
          "t": 48.89999997615814,
          "tiltX": 0,
          "tiltY": 0
        },
        {
          "x": 765.1259155273438,
          "y": 419.9132080078125,
          "p": 0.5,
          "t": 65.60000002384186,
          "tiltX": 0,
          "tiltY": 0
        },
        {
          "x": 765.1259155273438,
          "y": 435.36895751953125,
          "p": 0.5,
          "t": 65.60000002384186,
          "tiltX": 0,
          "tiltY": 0
        },
        {
          "x": 765.1259155273438,
          "y": 455.2734680175781,
          "p": 0.5,
          "t": 82.20000004768372,
          "tiltX": 0,
          "tiltY": 0
        },
        {
          "x": 766.0547485351562,
          "y": 467.3915100097656,
          "p": 0.5,
          "t": 82.20000004768372,
          "tiltX": 0,
          "tiltY": 0
        },
        {
          "x": 767.9427490234375,
          "y": 480.6250305175781,
          "p": 0.5,
          "t": 82.20000004768372,
          "tiltX": 0,
          "tiltY": 0
        },
        {
          "x": 769.7396240234375,
          "y": 490.5208435058594,
          "p": 0.5,
          "t": 99,
          "tiltX": 0,
          "tiltY": 0
        },
        {
          "x": 771.4931030273438,
          "y": 499.3012390136719,
          "p": 0.5,
          "t": 99,
          "tiltX": 0,
          "tiltY": 0
        },
        {
          "x": 772.1354370117188,
          "y": 502.521728515625,
          "p": 0.5,
          "t": 115.30000007152557,
          "tiltX": 0,
          "tiltY": 0
        },
        {
          "x": 772.66064453125,
          "y": 504.62677001953125,
          "p": 0.5,
          "t": 115.30000007152557,
          "tiltX": 0,
          "tiltY": 0
        },
        {
          "x": 773.32470703125,
          "y": 505.6206970214844,
          "p": 0.5,
          "t": 132.39999997615814,
          "tiltX": 0,
          "tiltY": 0
        },
        {
          "x": 773.7760620117188,
          "y": 505.84637451171875,
          "p": 0.5,
          "t": 132.39999997615814,
          "tiltX": 0,
          "tiltY": 0
        },
        {
          "x": 774.2274780273438,
          "y": 505.84637451171875,
          "p": 0.5,
          "t": 148.89999997615814,
          "tiltX": 0,
          "tiltY": 0
        },
        {
          "x": 775.2213745117188,
          "y": 505.84637451171875,
          "p": 0.5,
          "t": 148.89999997615814,
          "tiltX": 0,
          "tiltY": 0
        },
        {
          "x": 781.779541015625,
          "y": 505.02606201171875,
          "p": 0.5,
          "t": 164.70000004768372,
          "tiltX": 0,
          "tiltY": 0
        },
        {
          "x": 786.1111450195312,
          "y": 502.8559265136719,
          "p": 0.5,
          "t": 164.70000004768372,
          "tiltX": 0,
          "tiltY": 0
        },
        {
          "x": 788.2161865234375,
          "y": 502.326416015625,
          "p": 0.5,
          "t": 182.30000007152557,
          "tiltX": 0,
          "tiltY": 0
        },
        {
          "x": 794.7743530273438,
          "y": 499.045166015625,
          "p": 0.5,
          "t": 182.30000007152557,
          "tiltX": 0,
          "tiltY": 0
        },
        {
          "x": 801.5928955078125,
          "y": 494.78302001953125,
          "p": 0.5,
          "t": 182.30000007152557,
          "tiltX": 0,
          "tiltY": 0
        },
        {
          "x": 811.9879150390625,
          "y": 485.32989501953125,
          "p": 0.5,
          "t": 198.39999997615814,
          "tiltX": 0,
          "tiltY": 0
        },
        {
          "x": 819.18408203125,
          "y": 478.1293640136719,
          "p": 0.5,
          "t": 198.39999997615814,
          "tiltX": 0,
          "tiltY": 0
        },
        {
          "x": 827.4392700195312,
          "y": 469.86981201171875,
          "p": 0.5,
          "t": 214.70000004768372,
          "tiltX": 0,
          "tiltY": 0
        },
        {
          "x": 830.55126953125,
          "y": 465.1996765136719,
          "p": 0.5,
          "t": 214.70000004768372,
          "tiltX": 0,
          "tiltY": 0
        },
        {
          "x": 833.4375610351562,
          "y": 461.584228515625,
          "p": 0.5,
          "t": 232.30000007152557,
          "tiltX": 0,
          "tiltY": 0
        },
        {
          "x": 840.7725830078125,
          "y": 452.40887451171875,
          "p": 0.5,
          "t": 232.30000007152557,
          "tiltX": 0,
          "tiltY": 0
        },
        {
          "x": 846.7361450195312,
          "y": 446.44097900390625,
          "p": 0.5,
          "t": 232.30000007152557,
          "tiltX": 0,
          "tiltY": 0
        },
        {
          "x": 847.1875610351562,
          "y": 446.2109680175781,
          "p": 0.5,
          "t": 248.89999997615814,
          "tiltX": 0,
          "tiltY": 0
        },
        {
          "x": 847.4132080078125,
          "y": 446.2109680175781,
          "p": 0.5,
          "t": 248.89999997615814,
          "tiltX": 0,
          "tiltY": 0
        },
        {
          "x": 847.638916015625,
          "y": 446.4366455078125,
          "p": 0.5,
          "t": 265.60000002384186,
          "tiltX": 0,
          "tiltY": 0
        },
        {
          "x": 849.5703735351562,
          "y": 449.6571350097656,
          "p": 0.5,
          "t": 265.60000002384186,
          "tiltX": 0,
          "tiltY": 0
        },
        {
          "x": 850.6207275390625,
          "y": 451.7621765136719,
          "p": 0.5,
          "t": 282.3000000715256,
          "tiltX": 0,
          "tiltY": 0
        },
        {
          "x": 853.8975830078125,
          "y": 458.3203430175781,
          "p": 0.5,
          "t": 282.3000000715256,
          "tiltX": 0,
          "tiltY": 0
        },
        {
          "x": 857.5651245117188,
          "y": 469.3272705078125,
          "p": 0.5,
          "t": 299,
          "tiltX": 0,
          "tiltY": 0
        },
        {
          "x": 861.076416015625,
          "y": 478.107666015625,
          "p": 0.5,
          "t": 299,
          "tiltX": 0,
          "tiltY": 0
        },
        {
          "x": 864.5877075195312,
          "y": 486.8880310058594,
          "p": 0.5,
          "t": 315.60000002384186,
          "tiltX": 0,
          "tiltY": 0
        },
        {
          "x": 866.0286865234375,
          "y": 491.2196350097656,
          "p": 0.5,
          "t": 315.60000002384186,
          "tiltX": 0,
          "tiltY": 0
        },
        {
          "x": 868.9149780273438,
          "y": 494.83074951171875,
          "p": 0.5,
          "t": 315.60000002384186,
          "tiltX": 0,
          "tiltY": 0
        },
        {
          "x": 871.02001953125,
          "y": 495.881103515625,
          "p": 0.5,
          "t": 332.3000000715256,
          "tiltX": 0,
          "tiltY": 0
        },
        {
          "x": 872.013916015625,
          "y": 495.881103515625,
          "p": 0.5,
          "t": 332.3000000715256,
          "tiltX": 0,
          "tiltY": 0
        },
        {
          "x": 876.3455200195312,
          "y": 495.881103515625,
          "p": 0.5,
          "t": 349,
          "tiltX": 0,
          "tiltY": 0
        },
        {
          "x": 882.9036865234375,
          "y": 493.420166015625,
          "p": 0.5,
          "t": 349,
          "tiltX": 0,
          "tiltY": 0
        },
        {
          "x": 886.5147705078125,
          "y": 490.529541015625,
          "p": 0.5,
          "t": 365.7000000476837,
          "tiltX": 0,
          "tiltY": 0
        },
        {
          "x": 894.77001953125,
          "y": 483.19012451171875,
          "p": 0.5,
          "t": 365.7000000476837,
          "tiltX": 0,
          "tiltY": 0
        },
        {
          "x": 899.3533325195312,
          "y": 473.0946350097656,
          "p": 0.5,
          "t": 382.3000000715256,
          "tiltX": 0,
          "tiltY": 0
        },
        {
          "x": 900.9896240234375,
          "y": 466.5321350097656,
          "p": 0.5,
          "t": 382.3000000715256,
          "tiltX": 0,
          "tiltY": 0
        },
        {
          "x": 901.5147705078125,
          "y": 464.4227600097656,
          "p": 0.5,
          "t": 382.3000000715256,
          "tiltX": 0,
          "tiltY": 0
        },
        {
          "x": 902.4306030273438,
          "y": 453.4114685058594,
          "p": 0.5,
          "t": 399,
          "tiltX": 0,
          "tiltY": 0
        },
        {
          "x": 902.4306030273438,
          "y": 450.1866455078125,
          "p": 0.5,
          "t": 399,
          "tiltX": 0,
          "tiltY": 0
        },
        {
          "x": 902.4306030273438,
          "y": 449.7309265136719,
          "p": 0.5,
          "t": 415.60000002384186,
          "tiltX": 0,
          "tiltY": 0
        },
        {
          "x": 902.4306030273438,
          "y": 450.18231201171875,
          "p": 0.5,
          "t": 432.39999997615814,
          "tiltX": 0,
          "tiltY": 0
        },
        {
          "x": 902.4306030273438,
          "y": 450.6336975097656,
          "p": 0.5,
          "t": 432.39999997615814,
          "tiltX": 0,
          "tiltY": 0
        },
        {
          "x": 902.4306030273438,
          "y": 451.0850830078125,
          "p": 0.5,
          "t": 448.10000002384186,
          "tiltX": 0,
          "tiltY": 0
        },
        {
          "x": 902.4306030273438,
          "y": 456.5278015136719,
          "p": 0.5,
          "t": 448.10000002384186,
          "tiltX": 0,
          "tiltY": 0
        },
        {
          "x": 903.87158203125,
          "y": 460.8594055175781,
          "p": 0.5,
          "t": 465.60000002384186,
          "tiltX": 0,
          "tiltY": 0
        },
        {
          "x": 907.7604370117188,
          "y": 465.52520751953125,
          "p": 0.5,
          "t": 465.60000002384186,
          "tiltX": 0,
          "tiltY": 0
        },
        {
          "x": 914.787353515625,
          "y": 470.7942810058594,
          "p": 0.5,
          "t": 465.60000002384186,
          "tiltX": 0,
          "tiltY": 0
        },
        {
          "x": 920.2301025390625,
          "y": 473.1250305175781,
          "p": 0.5,
          "t": 482.3000000715256,
          "tiltX": 0,
          "tiltY": 0
        },
        {
          "x": 930.1259155273438,
          "y": 475.8203430175781,
          "p": 0.5,
          "t": 482.3000000715256,
          "tiltX": 0,
          "tiltY": 0
        },
        {
          "x": 932.23095703125,
          "y": 476.34552001953125,
          "p": 0.5,
          "t": 499,
          "tiltX": 0,
          "tiltY": 0
        },
        {
          "x": 942.1267700195312,
          "y": 476.34552001953125,
          "p": 0.5,
          "t": 499,
          "tiltX": 0,
          "tiltY": 0
        },
        {
          "x": 947.5695190429688,
          "y": 476.34552001953125,
          "p": 0.5,
          "t": 515.6000000238419,
          "tiltX": 0,
          "tiltY": 0
        },
        {
          "x": 950.7899780273438,
          "y": 476.34552001953125,
          "p": 0.5,
          "t": 515.6000000238419,
          "tiltX": 0,
          "tiltY": 0
        },
        {
          "x": 953.36376953125,
          "y": 473.76739501953125,
          "p": 0.5,
          "t": 532.3000000715256,
          "tiltX": 0,
          "tiltY": 0
        },
        {
          "x": 953.693603515625,
          "y": 472.7691345214844,
          "p": 0.5,
          "t": 532.3000000715256,
          "tiltX": 0,
          "tiltY": 0
        },
        {
          "x": 953.693603515625,
          "y": 469.5442810058594,
          "p": 0.5,
          "t": 532.3000000715256,
          "tiltX": 0,
          "tiltY": 0
        },
        {
          "x": 953.693603515625,
          "y": 466.3194580078125,
          "p": 0.5,
          "t": 548,
          "tiltX": 0,
          "tiltY": 0
        },
        {
          "x": 953.4635620117188,
          "y": 465.8637390136719,
          "p": 0.5,
          "t": 548,
          "tiltX": 0,
          "tiltY": 0
        },
        {
          "x": 953.2335815429688,
          "y": 465.6336975097656,
          "p": 0.5,
          "t": 565.7000000476837,
          "tiltX": 0,
          "tiltY": 0
        },
        {
          "x": 953.0035400390625,
          "y": 465.6336975097656,
          "p": 0.5,
          "t": 565.7000000476837,
          "tiltX": 0,
          "tiltY": 0
        },
        {
          "x": 952.5477905273438,
          "y": 465.8594055175781,
          "p": 0.5,
          "t": 582.2000000476837,
          "tiltX": 0,
          "tiltY": 0
        },
        {
          "x": 952.3177490234375,
          "y": 466.310791015625,
          "p": 0.5,
          "t": 582.2000000476837,
          "tiltX": 0,
          "tiltY": 0
        },
        {
          "x": 951.0286865234375,
          "y": 469.5312805175781,
          "p": 0.5,
          "t": 599,
          "tiltX": 0,
          "tiltY": 0
        },
        {
          "x": 949.7396240234375,
          "y": 472.75177001953125,
          "p": 0.5,
          "t": 599,
          "tiltX": 0,
          "tiltY": 0
        },
        {
          "x": 949.4054565429688,
          "y": 473.7456970214844,
          "p": 0.5,
          "t": 615.6000000238419,
          "tiltX": 0,
          "tiltY": 0
        },
        {
          "x": 949.4054565429688,
          "y": 476.9661560058594,
          "p": 0.5,
          "t": 615.6000000238419,
          "tiltX": 0,
          "tiltY": 0
        },
        {
          "x": 951.3368530273438,
          "y": 480.1866455078125,
          "p": 0.5,
          "t": 615.6000000238419,
          "tiltX": 0,
          "tiltY": 0
        },
        {
          "x": 955.2257690429688,
          "y": 484.0755310058594,
          "p": 0.5,
          "t": 632.3999999761581,
          "tiltX": 0,
          "tiltY": 0
        },
        {
          "x": 958.4462280273438,
          "y": 486.0069580078125,
          "p": 0.5,
          "t": 632.3999999761581,
          "tiltX": 0,
          "tiltY": 0
        },
        {
          "x": 962.77783203125,
          "y": 487.44793701171875,
          "p": 0.5,
          "t": 648.8999999761581,
          "tiltX": 0,
          "tiltY": 0
        },
        {
          "x": 964.8828735351562,
          "y": 487.9731140136719,
          "p": 0.5,
          "t": 648.8999999761581,
          "tiltX": 0,
          "tiltY": 0
        },
        {
          "x": 965.334228515625,
          "y": 487.9731140136719,
          "p": 0.5,
          "t": 665.7000000476837,
          "tiltX": 0,
          "tiltY": 0
        },
        {
          "x": 967.4392700195312,
          "y": 487.9731140136719,
          "p": 0.5,
          "t": 665.7000000476837,
          "tiltX": 0,
          "tiltY": 0
        },
        {
          "x": 967.8906860351562,
          "y": 487.51739501953125,
          "p": 0.5,
          "t": 681.8999999761581,
          "tiltX": 0,
          "tiltY": 0
        },
        {
          "x": 968.5547485351562,
          "y": 486.5191345214844,
          "p": 0.5,
          "t": 681.8999999761581,
          "tiltX": 0,
          "tiltY": 0
        },
        {
          "x": 968.5547485351562,
          "y": 486.0633850097656,
          "p": 0.5,
          "t": 681.8999999761581,
          "tiltX": 0,
          "tiltY": 0
        },
        {
          "x": 968.7804565429688,
          "y": 486.2890930175781,
          "p": 0.5,
          "t": 732.3999999761581,
          "tiltX": 0,
          "tiltY": 0
        },
        {
          "x": 968.7804565429688,
          "y": 486.5147705078125,
          "p": 0.5,
          "t": 732.3999999761581,
          "tiltX": 0,
          "tiltY": 0
        },
        {
          "x": 972.0573120117188,
          "y": 493.07293701171875,
          "p": 0.5,
          "t": 749.1000000238419,
          "tiltX": 0,
          "tiltY": 0
        },
        {
          "x": 972.7213745117188,
          "y": 494.0668640136719,
          "p": 0.5,
          "t": 749.1000000238419,
          "tiltX": 0,
          "tiltY": 0
        },
        {
          "x": 979.279541015625,
          "y": 497.3437805175781,
          "p": 0.5,
          "t": 749.1000000238419,
          "tiltX": 0,
          "tiltY": 0
        },
        {
          "x": 981.3845825195312,
          "y": 497.86895751953125,
          "p": 0.5,
          "t": 765.7000000476837,
          "tiltX": 0,
          "tiltY": 0
        },
        {
          "x": 993.5026245117188,
          "y": 498.7977600097656,
          "p": 0.5,
          "t": 765.7000000476837,
          "tiltX": 0,
          "tiltY": 0
        },
        {
          "x": 1003.3984985351562,
          "y": 498.7977600097656,
          "p": 0.5,
          "t": 782.3000000715256,
          "tiltX": 0,
          "tiltY": 0
        },
        {
          "x": 1018.8541870117188,
          "y": 495.8984680175781,
          "p": 0.5,
          "t": 782.3000000715256,
          "tiltX": 0,
          "tiltY": 0
        },
        {
          "x": 1033.4722900390625,
          "y": 488.0989685058594,
          "p": 0.5,
          "t": 798.3000000715256,
          "tiltX": 0,
          "tiltY": 0
        },
        {
          "x": 1047.1181640625,
          "y": 477.3741455078125,
          "p": 0.5,
          "t": 798.3000000715256,
          "tiltX": 0,
          "tiltY": 0
        },
        {
          "x": 1059.0625,
          "y": 461.4453430175781,
          "p": 0.5,
          "t": 815.7000000476837,
          "tiltX": 0,
          "tiltY": 0
        },
        {
          "x": 1064.65283203125,
          "y": 450.256103515625,
          "p": 0.5,
          "t": 815.7000000476837,
          "tiltX": 0,
          "tiltY": 0
        },
        {
          "x": 1068.381103515625,
          "y": 438.1336975097656,
          "p": 0.5,
          "t": 832.3000000715256,
          "tiltX": 0,
          "tiltY": 0
        },
        {
          "x": 1071.3802490234375,
          "y": 417.1094055175781,
          "p": 0.5,
          "t": 832.3000000715256,
          "tiltX": 0,
          "tiltY": 0
        },
        {
          "x": 1071.3802490234375,
          "y": 398.3116455078125,
          "p": 0.5,
          "t": 832.3000000715256,
          "tiltX": 0,
          "tiltY": 0
        },
        {
          "x": 1070.373291015625,
          "y": 376.1762390136719,
          "p": 0.5,
          "t": 849,
          "tiltX": 0,
          "tiltY": 0
        },
        {
          "x": 1066.388916015625,
          "y": 356.2673645019531,
          "p": 0.5,
          "t": 849,
          "tiltX": 0,
          "tiltY": 0
        },
        {
          "x": 1060.490478515625,
          "y": 339.56597900390625,
          "p": 0.5,
          "t": 865.3000000715256,
          "tiltX": 0,
          "tiltY": 0
        },
        {
          "x": 1052.760498046875,
          "y": 326.037353515625,
          "p": 0.5,
          "t": 865.3000000715256,
          "tiltX": 0,
          "tiltY": 0
        },
        {
          "x": 1050.82470703125,
          "y": 323.459228515625,
          "p": 0.5,
          "t": 882.3000000715256,
          "tiltX": 0,
          "tiltY": 0
        },
        {
          "x": 1045.377685546875,
          "y": 321.90106201171875,
          "p": 0.5,
          "t": 882.3000000715256,
          "tiltX": 0,
          "tiltY": 0
        },
        {
          "x": 1041.041748046875,
          "y": 321.90106201171875,
          "p": 0.5,
          "t": 898.8999999761581,
          "tiltX": 0,
          "tiltY": 0
        },
        {
          "x": 1034.010498046875,
          "y": 328.0469055175781,
          "p": 0.5,
          "t": 898.8999999761581,
          "tiltX": 0,
          "tiltY": 0
        },
        {
          "x": 1027.2440185546875,
          "y": 342.5390930175781,
          "p": 0.5,
          "t": 915.6000000238419,
          "tiltX": 0,
          "tiltY": 0
        },
        {
          "x": 1022.3698120117188,
          "y": 359.1059265136719,
          "p": 0.5,
          "t": 915.6000000238419,
          "tiltX": 0,
          "tiltY": 0
        },
        {
          "x": 1019.3663940429688,
          "y": 380.1258850097656,
          "p": 0.5,
          "t": 915.6000000238419,
          "tiltX": 0,
          "tiltY": 0
        },
        {
          "x": 1019.3663940429688,
          "y": 392.24395751953125,
          "p": 0.5,
          "t": 932,
          "tiltX": 0,
          "tiltY": 0
        },
        {
          "x": 1018.1510620117188,
          "y": 427.443603515625,
          "p": 0.5,
          "t": 932,
          "tiltX": 0,
          "tiltY": 0
        },
        {
          "x": 1018.1510620117188,
          "y": 478.97137451171875,
          "p": 0.5,
          "t": 948.6000000238419,
          "tiltX": 0,
          "tiltY": 0
        },
        {
          "x": 1019.2492065429688,
          "y": 508.72833251953125,
          "p": 0.5,
          "t": 948.6000000238419,
          "tiltX": 0,
          "tiltY": 0
        },
        {
          "x": 1020.78564453125,
          "y": 565.6987915039062,
          "p": 0.5,
          "t": 965.6000000238419,
          "tiltX": 0,
          "tiltY": 0
        },
        {
          "x": 1022.3524780273438,
          "y": 625.390625,
          "p": 0.5,
          "t": 965.6000000238419,
          "tiltX": 0,
          "tiltY": 0
        },
        {
          "x": 1022.3524780273438,
          "y": 663.3116455078125,
          "p": 0.5,
          "t": 982.3000000715256,
          "tiltX": 0,
          "tiltY": 0
        },
        {
          "x": 1022.3524780273438,
          "y": 680.9939575195312,
          "p": 0.5,
          "t": 982.3000000715256,
          "tiltX": 0,
          "tiltY": 0
        },
        {
          "x": 1022.3524780273438,
          "y": 703.1250610351562,
          "p": 0.5,
          "t": 982.3000000715256,
          "tiltX": 0,
          "tiltY": 0
        },
        {
          "x": 1022.3524780273438,
          "y": 721.91845703125,
          "p": 0.5,
          "t": 998.8000000715256,
          "tiltX": 0,
          "tiltY": 0
        },
        {
          "x": 1021.4063110351562,
          "y": 735.1519165039062,
          "p": 0.5,
          "t": 998.8000000715256,
          "tiltX": 0,
          "tiltY": 0
        },
        {
          "x": 1021.4063110351562,
          "y": 745.0477905273438,
          "p": 0.5,
          "t": 1015.7000000476837,
          "tiltX": 0,
          "tiltY": 0
        },
        {
          "x": 1021.4063110351562,
          "y": 749.37939453125,
          "p": 0.5,
          "t": 1015.7000000476837,
          "tiltX": 0,
          "tiltY": 0
        },
        {
          "x": 1022.0486450195312,
          "y": 752.599853515625,
          "p": 0.5,
          "t": 1031.6000000238419,
          "tiltX": 0,
          "tiltY": 0
        },
        {
          "x": 1022.0486450195312,
          "y": 752.8255615234375,
          "p": 0.5,
          "t": 1031.6000000238419,
          "tiltX": 0,
          "tiltY": 0
        },
        {
          "x": 1022.2743530273438,
          "y": 753.05126953125,
          "p": 0.5,
          "t": 1049.7000000476837,
          "tiltX": 0,
          "tiltY": 0
        },
        {
          "x": 1021.9401245117188,
          "y": 752.052978515625,
          "p": 0.5,
          "t": 1065.6000000238419,
          "tiltX": 0,
          "tiltY": 0
        },
        {
          "x": 1021.4844360351562,
          "y": 751.5972290039062,
          "p": 0.5,
          "t": 1065.6000000238419,
          "tiltX": 0,
          "tiltY": 0
        },
        {
          "x": 1018.2031860351562,
          "y": 745.8550415039062,
          "p": 0.5,
          "t": 1065.6000000238419,
          "tiltX": 0,
          "tiltY": 0
        },
        {
          "x": 1003.0426025390625,
          "y": 727.66064453125,
          "p": 0.5,
          "t": 1082.3000000715256,
          "tiltX": 0,
          "tiltY": 0
        },
        {
          "x": 983.2813110351562,
          "y": 708.9409790039062,
          "p": 0.5,
          "t": 1082.3000000715256,
          "tiltX": 0,
          "tiltY": 0
        },
        {
          "x": 972.8820190429688,
          "y": 699.4878540039062,
          "p": 0.5,
          "t": 1099,
          "tiltX": 0,
          "tiltY": 0
        },
        {
          "x": 943.7457275390625,
          "y": 678.849853515625,
          "p": 0.5,
          "t": 1099,
          "tiltX": 0,
          "tiltY": 0
        },
        {
          "x": 905.7986450195312,
          "y": 655.8116455078125,
          "p": 0.5,
          "t": 1115.7000000476837,
          "tiltX": 0,
          "tiltY": 0
        },
        {
          "x": 833.185791015625,
          "y": 616.8489990234375,
          "p": 0.5,
          "t": 1115.7000000476837,
          "tiltX": 0,
          "tiltY": 0
        },
        {
          "x": 768.63720703125,
          "y": 592.0225830078125,
          "p": 0.5,
          "t": 1132.3000000715256,
          "tiltX": 0,
          "tiltY": 0
        },
        {
          "x": 737.3134155273438,
          "y": 581.5798950195312,
          "p": 0.5,
          "t": 1132.3000000715256,
          "tiltX": 0,
          "tiltY": 0
        },
        {
          "x": 665.7161865234375,
          "y": 564.53125,
          "p": 0.5,
          "t": 1132.3000000715256,
          "tiltX": 0,
          "tiltY": 0
        },
        {
          "x": 642.4696655273438,
          "y": 559.474853515625,
          "p": 0.5,
          "t": 1149,
          "tiltX": 0,
          "tiltY": 0
        },
        {
          "x": 580.0521240234375,
          "y": 551.4713745117188,
          "p": 0.5,
          "t": 1149,
          "tiltX": 0,
          "tiltY": 0
        },
        {
          "x": 559.02783203125,
          "y": 550.46875,
          "p": 0.5,
          "t": 1165.8000000715256,
          "tiltX": 0,
          "tiltY": 0
        },
        {
          "x": 542.4566040039062,
          "y": 550.46875,
          "p": 0.5,
          "t": 1165.8000000715256,
          "tiltX": 0,
          "tiltY": 0
        },
        {
          "x": 538.1206665039062,
          "y": 551.9097290039062,
          "p": 0.5,
          "t": 1182.2000000476837,
          "tiltX": 0,
          "tiltY": 0
        },
        {
          "x": 538.1206665039062,
          "y": 552.1354370117188,
          "p": 0.5,
          "t": 1182.2000000476837,
          "tiltX": 0,
          "tiltY": 0
        },
        {
          "x": 538.5720825195312,
          "y": 552.1354370117188,
          "p": 0.5,
          "t": 1199.1000000238419,
          "tiltX": 0,
          "tiltY": 0
        },
        {
          "x": 539.5659790039062,
          "y": 552.46533203125,
          "p": 0.5,
          "t": 1199.1000000238419,
          "tiltX": 0,
          "tiltY": 0
        },
        {
          "x": 548.3463745117188,
          "y": 553.342041015625,
          "p": 0.5,
          "t": 1215.6000000238419,
          "tiltX": 0,
          "tiltY": 0
        },
        {
          "x": 560.4644165039062,
          "y": 553.342041015625,
          "p": 0.5,
          "t": 1215.6000000238419,
          "tiltX": 0,
          "tiltY": 0
        },
        {
          "x": 585.9331665039062,
          "y": 553.342041015625,
          "p": 0.5,
          "t": 1215.6000000238419,
          "tiltX": 0,
          "tiltY": 0
        },
        {
          "x": 611.4019165039062,
          "y": 551.3021240234375,
          "p": 0.5,
          "t": 1231.8000000715256,
          "tiltX": 0,
          "tiltY": 0
        },
        {
          "x": 668.3724365234375,
          "y": 548.2205200195312,
          "p": 0.5,
          "t": 1231.8000000715256,
          "tiltX": 0,
          "tiltY": 0
        },
        {
          "x": 725.3428955078125,
          "y": 546.6796875,
          "p": 0.5,
          "t": 1249,
          "tiltX": 0,
          "tiltY": 0
        },
        {
          "x": 744.1362915039062,
          "y": 545.6901245117188,
          "p": 0.5,
          "t": 1249,
          "tiltX": 0,
          "tiltY": 0
        },
        {
          "x": 782.0573120117188,
          "y": 543.1597290039062,
          "p": 0.5,
          "t": 1264.8000000715256,
          "tiltX": 0,
          "tiltY": 0
        },
        {
          "x": 860.7986450195312,
          "y": 537.9080200195312,
          "p": 0.5,
          "t": 1264.8000000715256,
          "tiltX": 0,
          "tiltY": 0
        },
        {
          "x": 906.8837280273438,
          "y": 532.3177490234375,
          "p": 0.5,
          "t": 1282.3000000715256,
          "tiltX": 0,
          "tiltY": 0
        },
        {
          "x": 955.6901245117188,
          "y": 526.5755615234375,
          "p": 0.5,
          "t": 1282.3000000715256,
          "tiltX": 0,
          "tiltY": 0
        },
        {
          "x": 1004.49658203125,
          "y": 520.8333740234375,
          "p": 0.5,
          "t": 1282.3000000715256,
          "tiltX": 0,
          "tiltY": 0
        },
        {
          "x": 1034.2535400390625,
          "y": 517.5260620117188,
          "p": 0.5,
          "t": 1299.1000000238419,
          "tiltX": 0,
          "tiltY": 0
        },
        {
          "x": 1056.3846435546875,
          "y": 517.5260620117188,
          "p": 0.5,
          "t": 1299.1000000238419,
          "tiltX": 0,
          "tiltY": 0
        },
        {
          "x": 1064.0538330078125,
          "y": 516.6710205078125,
          "p": 0.5,
          "t": 1315.7000000476837,
          "tiltX": 0,
          "tiltY": 0
        },
        {
          "x": 1072.834228515625,
          "y": 516.6710205078125,
          "p": 0.5,
          "t": 1315.7000000476837,
          "tiltX": 0,
          "tiltY": 0
        },
        {
          "x": 1080.5035400390625,
          "y": 514.96533203125,
          "p": 0.5,
          "t": 1332.3000000715256,
          "tiltX": 0,
          "tiltY": 0
        },
        {
          "x": 1082.6085205078125,
          "y": 514.435791015625,
          "p": 0.5,
          "t": 1332.3000000715256,
          "tiltX": 0,
          "tiltY": 0
        },
        {
          "x": 1082.834228515625,
          "y": 514.435791015625,
          "p": 0.5,
          "t": 1349,
          "tiltX": 0,
          "tiltY": 0
        },
        {
          "x": 1082.604248046875,
          "y": 514.435791015625,
          "p": 0.5,
          "t": 1393.1000000238419,
          "tiltX": 0,
          "tiltY": 0
        },
        {
          "x": 1082.3741455078125,
          "y": 514.435791015625,
          "p": 0.5,
          "t": 1415.1000000238419,
          "tiltX": 0,
          "tiltY": 0
        },
        {
          "x": 1082.1441650390625,
          "y": 514.6614990234375,
          "p": 0.5,
          "t": 1415.1000000238419,
          "tiltX": 0,
          "tiltY": 0
        },
        {
          "x": 1081.9140625,
          "y": 514.6614990234375,
          "p": 0.5,
          "t": 1433.2000000476837,
          "tiltX": 0,
          "tiltY": 0
        },
        {
          "x": 1081.68408203125,
          "y": 514.88720703125,
          "p": 0.5,
          "t": 1433.2000000476837,
          "tiltX": 0,
          "tiltY": 0
        },
        {
          "x": 1081.2283935546875,
          "y": 514.88720703125,
          "p": 0.5,
          "t": 1449,
          "tiltX": 0,
          "tiltY": 0
        },
        {
          "x": 1080.2301025390625,
          "y": 515.217041015625,
          "p": 0.5,
          "t": 1449,
          "tiltX": 0,
          "tiltY": 0
        },
        {
          "x": 1079.7744140625,
          "y": 515.217041015625,
          "p": 0.5,
          "t": 1449,
          "tiltX": 0,
          "tiltY": 0
        },
        {
          "x": 1079.318603515625,
          "y": 515.4427490234375,
          "p": 0.5,
          "t": 1465.3000000715256,
          "tiltX": 0,
          "tiltY": 0
        },
        {
          "x": 1079.088623046875,
          "y": 515.4427490234375,
          "p": 0.5,
          "t": 1465.3000000715256,
          "tiltX": 0,
          "tiltY": 0
        },
        {
          "x": 1078.6328125,
          "y": 515.4427490234375,
          "p": 0.5,
          "t": 1482.3000000715256,
          "tiltX": 0,
          "tiltY": 0
        },
        {
          "x": 1078.40283203125,
          "y": 515.4427490234375,
          "p": 0.5,
          "t": 1482.3000000715256,
          "tiltX": 0,
          "tiltY": 0
        },
        {
          "x": 1078.1728515625,
          "y": 515.4427490234375,
          "p": 0.5,
          "t": 1499,
          "tiltX": 0,
          "tiltY": 0
        },
        {
          "x": 1077.9427490234375,
          "y": 515.4427490234375,
          "p": 0.5,
          "t": 1499,
          "tiltX": 0,
          "tiltY": 0
        },
        {
          "x": 1077.7127685546875,
          "y": 515.4427490234375,
          "p": 0.5,
          "t": 1499,
          "tiltX": 0,
          "tiltY": 0
        },
        {
          "x": 1077.2569580078125,
          "y": 515.4427490234375,
          "p": 0.5,
          "t": 1515.6000000238419,
          "tiltX": 0,
          "tiltY": 0
        },
        {
          "x": 1076.80126953125,
          "y": 515.4427490234375,
          "p": 0.5,
          "t": 1515.6000000238419,
          "tiltX": 0,
          "tiltY": 0
        },
        {
          "x": 1076.5712890625,
          "y": 515.4427490234375,
          "p": 0.5,
          "t": 1532.3000000715256,
          "tiltX": 0,
          "tiltY": 0
        },
        {
          "x": 1076.3411865234375,
          "y": 515.4427490234375,
          "p": 0.5,
          "t": 1532.3000000715256,
          "tiltX": 0,
          "tiltY": 0
        },
        {
          "x": 1075.885498046875,
          "y": 515.4427490234375,
          "p": 0.5,
          "t": 1548.8999999761581,
          "tiltX": 0,
          "tiltY": 0
        },
        {
          "x": 1075.6553955078125,
          "y": 515.4427490234375,
          "p": 0.5,
          "t": 1548.8999999761581,
          "tiltX": 0,
          "tiltY": 0
        },
        {
          "x": 1075.6553955078125,
          "y": 515.2127075195312,
          "p": 0.5,
          "t": 1590.8000000715256,
          "tiltX": 0,
          "tiltY": 0
        }
      ]
    }
  ]
}